firestore_utils/__init__.py
firestore_utils/exceptions.py
firestore_utils/firestore_collection.py
firestore_utils/scripts/__init__.py
firestore_utils-0.2.1.dist-info/METADATA
firestore_utils-0.2.1.dist-info/WHEEL
firestore_utils-0.2.1.dist-info/top_level.txt
firestore_utils-0.2.1.dist-info/RECORD
